{
  "POIs": [
    {
      "fit": [
        -0.025775833055377007,
        -8.096032615867443e-06,
        0.025892451405525208
      ],
      "name": "r"
    }
  ],
  "method": "default",
  "params": [
    {
      "fit": [
        -0.9938571453094482,
        -8.881784197001252e-16,
        0.9943654537200928
      ],
      "groups": [],
      "impact_r": 4.864935363002587e-05,
      "name": "CMS_Trigger_emu_13TeV",
      "prefit": [
        -0.9999999999999999,
        0.0,
        0.9999999999999999
      ],
      "r": [
        -5.6745386245893314e-05,
        -8.096032615867443e-06,
        -5.471444092108868e-05
      ],
      "type": "Gaussian"
    },
    {
      "fit": [
        -0.9938571453094482,
        -8.881784197001252e-16,
        0.9943654537200928
      ],
      "groups": [],
      "impact_r": 4.764974983118009e-05,
      "name": "CMS_eff_btag_2016",
      "prefit": [
        -0.9999999999999999,
        0.0,
        0.9999999999999999
      ],
      "r": [
        -5.569464701693505e-05,
        -8.096032615867443e-06,
        -5.574578244704753e-05
      ],
      "type": "Gaussian"
    },
    {
      "fit": [
        -0.9938571453094482,
        -8.881784197001252e-16,
        0.9943654537200928
      ],
      "groups": [],
      "impact_r": 4.762414573633578e-05,
      "name": "CMS_eff_btag_2017",
      "prefit": [
        -0.9999999999999999,
        0.0,
        0.9999999999999999
      ],
      "r": [
        -5.572017835220322e-05,
        -8.096032615867443e-06,
        -5.572017835220322e-05
      ],
      "type": "Gaussian"
    },
    {
      "fit": [
        -0.9938571453094482,
        -8.881784197001252e-16,
        0.9943654537200928
      ],
      "groups": [],
      "impact_r": 4.767548853124026e-05,
      "name": "CMS_eff_btag_2018",
      "prefit": [
        -0.9999999999999999,
        0.0,
        0.9999999999999999
      ],
      "r": [
        -5.5668897402938455e-05,
        -8.096032615867443e-06,
        -5.5771521147107705e-05
      ],
      "type": "Gaussian"
    },
    {
      "fit": [
        -0.9938571453094482,
        -8.881784197001252e-16,
        0.9943654537200928
      ],
      "groups": [],
      "impact_r": 4.864935363002587e-05,
      "name": "CMS_eff_e",
      "prefit": [
        -0.9999999999999999,
        0.0,
        0.9999999999999999
      ],
      "r": [
        -5.6745386245893314e-05,
        -8.096032615867443e-06,
        -5.471444092108868e-05
      ],
      "type": "Gaussian"
    },
    {
      "fit": [
        -0.9938571453094482,
        -8.881784197001252e-16,
        0.9943654537200928
      ],
      "groups": [],
      "impact_r": 4.864935363002587e-05,
      "name": "CMS_eff_m",
      "prefit": [
        -0.9999999999999999,
        0.0,
        0.9999999999999999
      ],
      "r": [
        -5.6745386245893314e-05,
        -8.096032615867443e-06,
        -5.471444092108868e-05
      ],
      "type": "Gaussian"
    },
    {
      "fit": [
        -0.1584239900112152,
        0.0,
        0.1587371677160263
      ],
      "groups": [],
      "impact_r": 4.762414573633578e-05,
      "name": "CMS_hem_nuisance_res_e_ggH",
      "prefit": [
        -0.1595,
        0.0,
        0.1595
      ],
      "r": [
        -5.572017835220322e-05,
        -8.096032615867443e-06,
        -5.572017835220322e-05
      ],
      "type": "Gaussian"
    },
    {
      "fit": [
        -0.19898881018161774,
        0.0,
        0.19930197298526764
      ],
      "groups": [],
      "impact_r": 4.762414573633578e-05,
      "name": "CMS_hem_nuisance_res_e_qqH",
      "prefit": [
        -0.2003,
        0.0,
        0.2003
      ],
      "r": [
        -5.572017835220322e-05,
        -8.096032615867443e-06,
        -5.572017835220322e-05
      ],
      "type": "Gaussian"
    },
    {
      "fit": [
        -0.24959540367126465,
        0.0,
        0.24990856647491455
      ],
      "groups": [],
      "impact_r": 4.762414573633578e-05,
      "name": "CMS_hem_nuisance_res_m_ggH",
      "prefit": [
        -0.2512,
        0.0,
        0.2512
      ],
      "r": [
        -5.572017835220322e-05,
        -8.096032615867443e-06,
        -5.572017835220322e-05
      ],
      "type": "Gaussian"
    },
    {
      "fit": [
        -0.18854933977127075,
        0.0,
        0.18886250257492065
      ],
      "groups": [],
      "impact_r": 4.762414573633578e-05,
      "name": "CMS_hem_nuisance_res_m_qqH",
      "prefit": [
        -0.1898,
        0.0,
        0.1898
      ],
      "r": [
        -5.572017835220322e-05,
        -8.096032615867443e-06,
        -5.572017835220322e-05
      ],
      "type": "Gaussian"
    },
    {
      "fit": [
        -0.035238202661275864,
        0.0,
        0.03555137291550636
      ],
      "groups": [],
      "impact_r": 4.762414573633578e-05,
      "name": "CMS_hem_nuisance_scale_e_ggH",
      "prefit": [
        -0.0356,
        0.0,
        0.0356
      ],
      "r": [
        -5.572017835220322e-05,
        -8.096032615867443e-06,
        -5.572017835220322e-05
      ],
      "type": "Gaussian"
    },
    {
      "fit": [
        -0.03692840412259102,
        0.0,
        0.03724157437682152
      ],
      "groups": [],
      "impact_r": 4.762414573633578e-05,
      "name": "CMS_hem_nuisance_scale_e_qqH",
      "prefit": [
        -0.03730000000000001,
        0.0,
        0.03730000000000001
      ],
      "r": [
        -5.572017835220322e-05,
        -8.096032615867443e-06,
        -5.572017835220322e-05
      ],
      "type": "Gaussian"
    },
    {
      "fit": [
        -0.032036297023296356,
        0.0,
        0.032036297023296356
      ],
      "groups": [],
      "impact_r": 4.762414573633578e-05,
      "name": "CMS_hem_nuisance_scale_m_ggH",
      "prefit": [
        -0.0322,
        0.0,
        0.0322
      ],
      "r": [
        -5.572017835220322e-05,
        -8.096032615867443e-06,
        -5.572017835220322e-05
      ],
      "type": "Gaussian"
    },
    {
      "fit": [
        -0.031538836658000946,
        0.0,
        0.031538836658000946
      ],
      "groups": [],
      "impact_r": 4.762414573633578e-05,
      "name": "CMS_hem_nuisance_scale_m_qqH",
      "prefit": [
        -0.031700000000000006,
        0.0,
        0.031700000000000006
      ],
      "r": [
        -5.572017835220322e-05,
        -8.096032615867443e-06,
        -5.572017835220322e-05
      ],
      "type": "Gaussian"
    },
    {
      "fit": [
        -0.9938571453094482,
        -8.881784197001252e-16,
        0.9943654537200928
      ],
      "groups": [],
      "impact_r": 4.7941977754817344e-05,
      "name": "CMS_lumi_2016_13TeV",
      "prefit": [
        -0.9999999999999999,
        0.0,
        0.9999999999999999
      ],
      "r": [
        -5.603801037068479e-05,
        -8.096032615867443e-06,
        -5.5404107115464285e-05
      ],
      "type": "Gaussian"
    },
    {
      "fit": [
        -0.9938571453094482,
        -8.881784197001252e-16,
        0.9943654537200928
      ],
      "groups": [],
      "impact_r": 4.792917206941638e-05,
      "name": "CMS_lumi_2017_13TeV",
      "prefit": [
        -0.9999999999999999,
        0.0,
        0.9999999999999999
      ],
      "r": [
        -5.6025204685283825e-05,
        -8.096032615867443e-06,
        -5.54168364033103e-05
      ],
      "type": "Gaussian"
    },
    {
      "fit": [
        -0.9938571453094482,
        -8.881784197001252e-16,
        0.9943654537200928
      ],
      "groups": [],
      "impact_r": 4.824443931283895e-05,
      "name": "CMS_lumi_2018_13TeV",
      "prefit": [
        -0.9999999999999999,
        0.0,
        0.9999999999999999
      ],
      "r": [
        -5.634047192870639e-05,
        -8.096032615867443e-06,
        -5.5106993386289105e-05
      ],
      "type": "Gaussian"
    },
    {
      "fit": [
        -0.9938571453094482,
        -8.881784197001252e-16,
        0.9943654537200928
      ],
      "groups": [],
      "impact_r": 4.803776573680807e-05,
      "name": "CMS_pileup_2016",
      "prefit": [
        -0.9999999999999999,
        0.0,
        0.9999999999999999
      ],
      "r": [
        -5.5288197472691536e-05,
        -8.096032615867443e-06,
        -5.613379835267551e-05
      ],
      "type": "Gaussian"
    },
    {
      "fit": [
        -0.9938571453094482,
        -8.881784197001252e-16,
        0.9943654537200928
      ],
      "groups": [],
      "impact_r": 4.806411197932903e-05,
      "name": "CMS_pileup_2017",
      "prefit": [
        -0.9999999999999999,
        0.0,
        0.9999999999999999
      ],
      "r": [
        -5.5237513151951134e-05,
        -8.096032615867443e-06,
        -5.616014459519647e-05
      ],
      "type": "Gaussian"
    },
    {
      "fit": [
        -0.9938571453094482,
        -8.881784197001252e-16,
        0.9943654537200928
      ],
      "groups": [],
      "impact_r": 4.837886262976099e-05,
      "name": "CMS_pileup_2018",
      "prefit": [
        -0.9999999999999999,
        0.0,
        0.9999999999999999
      ],
      "r": [
        -5.498739847098477e-05,
        -8.096032615867443e-06,
        -5.647489524562843e-05
      ],
      "type": "Gaussian"
    },
    {
      "fit": [
        -0.9938571453094482,
        -8.881784197001252e-16,
        0.9943654537200928
      ],
      "groups": [],
      "impact_r": 4.76753029943211e-05,
      "name": "CMS_prefiring_2016",
      "prefit": [
        -0.9999999999999999,
        0.0,
        0.9999999999999999
      ],
      "r": [
        -5.566908293985762e-05,
        -8.096032615867443e-06,
        -5.5771335610188544e-05
      ],
      "type": "Gaussian"
    },
    {
      "fit": [
        -0.9938571453094482,
        -8.881784197001252e-16,
        0.9943654537200928
      ],
      "groups": [],
      "impact_r": 4.772676948050503e-05,
      "name": "CMS_prefiring_2017",
      "prefit": [
        -0.9999999999999999,
        0.0,
        0.9999999999999999
      ],
      "r": [
        -5.56177765247412e-05,
        -8.096032615867443e-06,
        -5.582280209637247e-05
      ],
      "type": "Gaussian"
    },
    {
      "fit": [
        -0.9938571453094482,
        -8.881784197001252e-16,
        0.9943654537200928
      ],
      "groups": [],
      "impact_r": 4.762414573633578e-05,
      "name": "CMS_res_e",
      "prefit": [
        -0.9999999999999999,
        0.0,
        0.9999999999999999
      ],
      "r": [
        -5.572017835220322e-05,
        -8.096032615867443e-06,
        -5.572017835220322e-05
      ],
      "type": "Gaussian"
    },
    {
      "fit": [
        -0.9938571453094482,
        -8.881784197001252e-16,
        0.9943654537200928
      ],
      "groups": [],
      "impact_r": 4.7778083171579055e-05,
      "name": "CMS_res_j_2016",
      "prefit": [
        -0.9999999999999999,
        0.0,
        0.9999999999999999
      ],
      "r": [
        -5.544020314118825e-05,
        -8.096032615867443e-06,
        -5.58741157874465e-05
      ],
      "type": "Gaussian"
    },
    {
      "fit": [
        -0.9938571453094482,
        -8.881784197001252e-16,
        0.9943654537200928
      ],
      "groups": [],
      "impact_r": 4.7881696445983835e-05,
      "name": "CMS_res_j_2017",
      "prefit": [
        -0.9999999999999999,
        0.0,
        0.9999999999999999
      ],
      "r": [
        -5.538940240512602e-05,
        -8.096032615867443e-06,
        -5.597772906185128e-05
      ],
      "type": "Gaussian"
    },
    {
      "fit": [
        -0.9938571453094482,
        -8.881784197001252e-16,
        0.9943654537200928
      ],
      "groups": [],
      "impact_r": 4.775239540322218e-05,
      "name": "CMS_res_j_2018",
      "prefit": [
        -0.9999999999999999,
        0.0,
        0.9999999999999999
      ],
      "r": [
        -5.531384886126034e-05,
        -8.096032615867443e-06,
        -5.5848428019089624e-05
      ],
      "type": "Gaussian"
    },
    {
      "fit": [
        -0.9938571453094482,
        -8.881784197001252e-16,
        0.9943654537200928
      ],
      "groups": [],
      "impact_r": 4.764972436532844e-05,
      "name": "CMS_scale_e",
      "prefit": [
        -0.9999999999999999,
        0.0,
        0.9999999999999999
      ],
      "r": [
        -5.574575698119588e-05,
        -8.096032615867443e-06,
        -5.572017835220322e-05
      ],
      "type": "Gaussian"
    },
    {
      "fit": [
        -0.9938571453094482,
        -8.881784197001252e-16,
        0.9943654537200928
      ],
      "groups": [],
      "impact_r": 4.798548798135016e-05,
      "name": "CMS_scale_j_Absolute",
      "prefit": [
        -0.9999999999999999,
        0.0,
        0.9999999999999999
      ],
      "r": [
        -5.5138429161161184e-05,
        -8.096032615867443e-06,
        -5.6081520597217605e-05
      ],
      "type": "Gaussian"
    },
    {
      "fit": [
        -0.9938571453094482,
        -8.881784197001252e-16,
        0.9943654537200928
      ],
      "groups": [],
      "impact_r": 4.764974983118009e-05,
      "name": "CMS_scale_j_Absolute_2016",
      "prefit": [
        -0.9999999999999999,
        0.0,
        0.9999999999999999
      ],
      "r": [
        -5.56182385480497e-05,
        -8.096032615867443e-06,
        -5.574578244704753e-05
      ],
      "type": "Gaussian"
    },
    {
      "fit": [
        -0.9938571453094482,
        -8.881784197001252e-16,
        0.9943654537200928
      ],
      "groups": [],
      "impact_r": 4.7701092626084574e-05,
      "name": "CMS_scale_j_Absolute_2017",
      "prefit": [
        -0.9999999999999999,
        0.0,
        0.9999999999999999
      ],
      "r": [
        -5.564336242969148e-05,
        -8.096032615867443e-06,
        -5.579712524195202e-05
      ],
      "type": "Gaussian"
    },
    {
      "fit": [
        -0.9938571453094482,
        -8.881784197001252e-16,
        0.9943654537200928
      ],
      "groups": [],
      "impact_r": 4.772676948050503e-05,
      "name": "CMS_scale_j_Absolute_2018",
      "prefit": [
        -0.9999999999999999,
        0.0,
        0.9999999999999999
      ],
      "r": [
        -5.56177765247412e-05,
        -8.096032615867443e-06,
        -5.582280209637247e-05
      ],
      "type": "Gaussian"
    },
    {
      "fit": [
        -0.9938571453094482,
        -8.881784197001252e-16,
        0.9943654537200928
      ],
      "groups": [],
      "impact_r": 4.772656211571302e-05,
      "name": "CMS_scale_j_BBEC1",
      "prefit": [
        -0.9999999999999999,
        0.0,
        0.9999999999999999
      ],
      "r": [
        -5.556703399633989e-05,
        -8.096032615867443e-06,
        -5.5822594731580466e-05
      ],
      "type": "Gaussian"
    },
    {
      "fit": [
        -0.9938571453094482,
        -8.881784197001252e-16,
        0.9943654537200928
      ],
      "groups": [],
      "impact_r": 4.762414573633578e-05,
      "name": "CMS_scale_j_BBEC1_2016",
      "prefit": [
        -0.9999999999999999,
        0.0,
        0.9999999999999999
      ],
      "r": [
        -5.564349703490734e-05,
        -8.096032615867443e-06,
        -5.572017835220322e-05
      ],
      "type": "Gaussian"
    },
    {
      "fit": [
        -0.9938571453094482,
        -8.881784197001252e-16,
        0.9943654537200928
      ],
      "groups": [],
      "impact_r": 4.764974983118009e-05,
      "name": "CMS_scale_j_BBEC1_2017",
      "prefit": [
        -0.9999999999999999,
        0.0,
        0.9999999999999999
      ],
      "r": [
        -5.572017835220322e-05,
        -8.096032615867443e-06,
        -5.574578244704753e-05
      ],
      "type": "Gaussian"
    },
    {
      "fit": [
        -0.9938571453094482,
        -8.881784197001252e-16,
        0.9943654537200928
      ],
      "groups": [],
      "impact_r": 4.770092164108064e-05,
      "name": "CMS_scale_j_BBEC1_2018",
      "prefit": [
        -0.9999999999999999,
        0.0,
        0.9999999999999999
      ],
      "r": [
        -5.564346065511927e-05,
        -8.096032615867443e-06,
        -5.5796954256948084e-05
      ],
      "type": "Gaussian"
    },
    {
      "fit": [
        -0.9938571453094482,
        -8.881784197001252e-16,
        0.9943654537200928
      ],
      "groups": [],
      "impact_r": 4.775239540322218e-05,
      "name": "CMS_scale_j_EC2",
      "prefit": [
        -0.9999999999999999,
        0.0,
        0.9999999999999999
      ],
      "r": [
        -5.559256169362925e-05,
        -8.096032615867443e-06,
        -5.5848428019089624e-05
      ],
      "type": "Gaussian"
    },
    {
      "fit": [
        -0.9938571453094482,
        -8.881784197001252e-16,
        0.9943654537200928
      ],
      "groups": [],
      "impact_r": 4.7649553380324505e-05,
      "name": "CMS_scale_j_EC2_2016",
      "prefit": [
        -0.9999999999999999,
        0.0,
        0.9999999999999999
      ],
      "r": [
        -5.566908293985762e-05,
        -8.096032615867443e-06,
        -5.574558599619195e-05
      ],
      "type": "Gaussian"
    },
    {
      "fit": [
        -0.9938571453094482,
        -8.881784197001252e-16,
        0.9943654537200928
      ],
      "groups": [],
      "impact_r": 4.767548853124026e-05,
      "name": "CMS_scale_j_EC2_2017",
      "prefit": [
        -0.9999999999999999,
        0.0,
        0.9999999999999999
      ],
      "r": [
        -5.569464701693505e-05,
        -8.096032615867443e-06,
        -5.5771521147107705e-05
      ],
      "type": "Gaussian"
    },
    {
      "fit": [
        -0.9938571453094482,
        -8.881784197001252e-16,
        0.9943654537200928
      ],
      "groups": [],
      "impact_r": 4.775239540322218e-05,
      "name": "CMS_scale_j_EC2_2018",
      "prefit": [
        -0.9999999999999999,
        0.0,
        0.9999999999999999
      ],
      "r": [
        -5.559256169362925e-05,
        -8.096032615867443e-06,
        -5.5848428019089624e-05
      ],
      "type": "Gaussian"
    },
    {
      "fit": [
        -0.9938571453094482,
        -8.881784197001252e-16,
        0.9943654537200928
      ],
      "groups": [],
      "impact_r": 4.783010263054166e-05,
      "name": "CMS_scale_j_FlavorQCD",
      "prefit": [
        -0.9999999999999999,
        0.0,
        0.9999999999999999
      ],
      "r": [
        -5.52890523977112e-05,
        -8.096032615867443e-06,
        -5.59261352464091e-05
      ],
      "type": "Gaussian"
    },
    {
      "fit": [
        -0.9938571453094482,
        -8.881784197001252e-16,
        0.9943654537200928
      ],
      "groups": [],
      "impact_r": 4.7778297812328674e-05,
      "name": "CMS_scale_j_HF",
      "prefit": [
        -0.9999999999999999,
        0.0,
        0.9999999999999999
      ],
      "r": [
        -5.544020314118825e-05,
        -8.096032615867443e-06,
        -5.587433042819612e-05
      ],
      "type": "Gaussian"
    },
    {
      "fit": [
        -0.9938571453094482,
        -8.881784197001252e-16,
        0.9943654537200928
      ],
      "groups": [],
      "impact_r": 4.7649429689045064e-05,
      "name": "CMS_scale_j_HF_2016",
      "prefit": [
        -0.9999999999999999,
        0.0,
        0.9999999999999999
      ],
      "r": [
        -5.574546230491251e-05,
        -8.096032615867443e-06,
        -5.56691265956033e-05
      ],
      "type": "Gaussian"
    },
    {
      "fit": [
        -0.9938571453094482,
        -8.881784197001252e-16,
        0.9943654537200928
      ],
      "groups": [],
      "impact_r": 4.767548853124026e-05,
      "name": "CMS_scale_j_HF_2017",
      "prefit": [
        -0.9999999999999999,
        0.0,
        0.9999999999999999
      ],
      "r": [
        -5.572017835220322e-05,
        -8.096032615867443e-06,
        -5.5771521147107705e-05
      ],
      "type": "Gaussian"
    },
    {
      "fit": [
        -0.9938571453094482,
        -8.881784197001252e-16,
        0.9943654537200928
      ],
      "groups": [],
      "impact_r": 4.764966979564633e-05,
      "name": "CMS_scale_j_HF_2018",
      "prefit": [
        -0.9999999999999999,
        0.0,
        0.9999999999999999
      ],
      "r": [
        -5.5745702411513776e-05,
        -8.096032615867443e-06,
        -5.569465065491386e-05
      ],
      "type": "Gaussian"
    },
    {
      "fit": [
        -0.9938571453094482,
        -8.881784197001252e-16,
        0.9943654537200928
      ],
      "groups": [],
      "impact_r": 4.775254819833208e-05,
      "name": "CMS_scale_j_RelativeBal",
      "prefit": [
        -0.9999999999999999,
        0.0,
        0.9999999999999999
      ],
      "r": [
        -5.584858081419952e-05,
        -8.096032615867443e-06,
        -5.5415115639334545e-05
      ],
      "type": "Gaussian"
    },
    {
      "fit": [
        -0.9938571453094482,
        -8.881784197001252e-16,
        0.9943654537200928
      ],
      "groups": [],
      "impact_r": 4.7675408495706506e-05,
      "name": "CMS_scale_j_RelativeSample_2016",
      "prefit": [
        -0.9999999999999999,
        0.0,
        0.9999999999999999
      ],
      "r": [
        -5.577144111157395e-05,
        -8.096032615867443e-06,
        -5.5668973800493404e-05
      ],
      "type": "Gaussian"
    },
    {
      "fit": [
        -0.9938571453094482,
        -8.881784197001252e-16,
        0.9943654537200928
      ],
      "groups": [],
      "impact_r": 4.7752377213328145e-05,
      "name": "CMS_scale_j_RelativeSample_2017",
      "prefit": [
        -0.9999999999999999,
        0.0,
        0.9999999999999999
      ],
      "r": [
        -5.584840982919559e-05,
        -8.096032615867443e-06,
        -5.56691265956033e-05
      ],
      "type": "Gaussian"
    },
    {
      "fit": [
        -0.9938571453094482,
        -8.881784197001252e-16,
        0.9943654537200928
      ],
      "groups": [],
      "impact_r": 4.775254819833208e-05,
      "name": "CMS_scale_j_RelativeSample_2018",
      "prefit": [
        -0.9999999999999999,
        0.0,
        0.9999999999999999
      ],
      "r": [
        -5.584858081419952e-05,
        -8.096032615867443e-06,
        -5.54910657228902e-05
      ],
      "type": "Gaussian"
    },
    {
      "fit": [
        -0.9938571453094482,
        -8.881784197001252e-16,
        0.9943654537200928
      ],
      "groups": [],
      "impact_r": 4.767548853124026e-05,
      "name": "CMS_scale_m",
      "prefit": [
        -0.9999999999999999,
        0.0,
        0.9999999999999999
      ],
      "r": [
        -5.569464701693505e-05,
        -8.096032615867443e-06,
        -5.5771521147107705e-05
      ],
      "type": "Gaussian"
    },
    {
      "fit": [
        -0.9938571453094482,
        -8.881784197001252e-16,
        0.9943655133247375
      ],
      "groups": [],
      "impact_r": 4.86179724248359e-05,
      "name": "CMS_scale_met_2016",
      "prefit": [
        -0.9999999999999999,
        0.0,
        0.9999999999999999
      ],
      "r": [
        -5.493764183484018e-05,
        -8.096032615867443e-06,
        -5.671400504070334e-05
      ],
      "type": "Gaussian"
    },
    {
      "fit": [
        -0.993857204914093,
        -8.881784197001252e-16,
        0.9943655133247375
      ],
      "groups": [],
      "impact_r": 4.8538642658968456e-05,
      "name": "CMS_scale_met_2017",
      "prefit": [
        -0.9999999999999999,
        0.0,
        0.9999999999999999
      ],
      "r": [
        -5.508624963113107e-05,
        -8.096032615867443e-06,
        -5.66346752748359e-05
      ],
      "type": "Gaussian"
    },
    {
      "fit": [
        -0.993857204914093,
        -8.881784197001252e-16,
        0.9943655133247375
      ],
      "groups": [],
      "impact_r": 4.8994048484019004e-05,
      "name": "CMS_scale_met_2018",
      "prefit": [
        -0.9999999999999999,
        0.0,
        0.9999999999999999
      ],
      "r": [
        -5.478835373651236e-05,
        -8.096032615867443e-06,
        -5.709008109988645e-05
      ],
      "type": "Gaussian"
    },
    {
      "fit": [
        -0.9938572645187378,
        -8.881784197001252e-16,
        0.9943655729293823
      ],
      "groups": [],
      "impact_r": 4.938901656714734e-05,
      "name": "QCDscale_ggH",
      "prefit": [
        -0.9999999999999999,
        0.0,
        0.9999999999999999
      ],
      "r": [
        -5.395113112172112e-05,
        -8.096032615867443e-06,
        -5.748504918301478e-05
      ],
      "type": "Gaussian"
    },
    {
      "fit": [
        -0.9938571453094482,
        -8.881784197001252e-16,
        0.9943654537200928
      ],
      "groups": [],
      "impact_r": 4.7759933295310475e-05,
      "name": "QCDscale_qqH",
      "prefit": [
        -0.9999999999999999,
        0.0,
        0.9999999999999999
      ],
      "r": [
        -5.558442717301659e-05,
        -8.096032615867443e-06,
        -5.585596591117792e-05
      ],
      "type": "Gaussian"
    },
    {
      "fit": [
        -0.9938571453094482,
        -8.881784197001252e-16,
        0.9943654537200928
      ],
      "groups": [],
      "impact_r": 4.813329178432468e-05,
      "name": "acceptance_pdf_gg",
      "prefit": [
        -0.9999999999999999,
        0.0,
        0.9999999999999999
      ],
      "r": [
        -5.622932440019213e-05,
        -8.096032615867443e-06,
        -5.521037019207142e-05
      ],
      "type": "Gaussian"
    },
    {
      "fit": [
        -0.993857204914093,
        -8.881784197001252e-16,
        0.9943655133247375
      ],
      "groups": [],
      "impact_r": 4.7966555939638056e-05,
      "name": "acceptance_pdf_vbf",
      "prefit": [
        -0.9999999999999999,
        0.0,
        0.9999999999999999
      ],
      "r": [
        -5.60625885555055e-05,
        -8.096032615867443e-06,
        -5.537740798899904e-05
      ],
      "type": "Gaussian"
    },
    {
      "fit": [
        -0.9938571453094482,
        -8.881784197001252e-16,
        0.9943654537200928
      ],
      "groups": [],
      "impact_r": 4.7739618821651675e-05,
      "name": "acceptance_scale_gg",
      "prefit": [
        -0.9999999999999999,
        0.0,
        0.9999999999999999
      ],
      "r": [
        -5.583565143751912e-05,
        -8.096032615867443e-06,
        -5.5604614317417145e-05
      ],
      "type": "Gaussian"
    },
    {
      "fit": [
        0.6574262976646423,
        0.8211551308631897,
        0.9775756001472473
      ],
      "groups": [],
      "impact_r": 0.013537783221181598,
      "name": "env_pdf_vbf_bern3_p0",
      "prefit": [
        0.819957704272614,
        0.819957704272614,
        0.819957704272614
      ],
      "r": [
        0.013529687188565731,
        -8.096032615867443e-06,
        -0.012968477793037891
      ],
      "type": "Unconstrained"
    },
    {
      "fit": [
        0.8303985595703125,
        0.9210965037345886,
        1.0018497705459595
      ],
      "groups": [],
      "impact_r": 0.01051986864877108,
      "name": "env_pdf_vbf_bern3_p1",
      "prefit": [
        0.920370036855271,
        0.920370036855271,
        0.920370036855271
      ],
      "r": [
        -0.010527964681386948,
        -8.096032615867443e-06,
        0.00950781349092722
      ],
      "type": "Unconstrained"
    },
    {
      "fit": [
        0.6537001729011536,
        0.7195959091186523,
        0.7903371453285217
      ],
      "groups": [],
      "impact_r": 0.006455354347053799,
      "name": "env_pdf_vbf_bern3_p2",
      "prefit": [
        0.7198203205358045,
        0.7198203205358045,
        0.7198203205358045
      ],
      "r": [
        0.006033303216099739,
        -8.096032615867443e-06,
        -0.006463450379669666
      ],
      "type": "Unconstrained"
    },
    {
      "fit": [
        1316.1602783203125,
        1358.0,
        1400.8988037109375
      ],
      "groups": [],
      "impact_r": 0.013106374955896172,
      "name": "shapeBkg_bkg_vbf__norm",
      "prefit": [
        1358.0,
        1358.0,
        1358.0
      ],
      "r": [
        0.012807747349143028,
        -8.096032615867443e-06,
        -0.01311447098851204
      ],
      "type": "Unconstrained"
    }
  ]
}